aollio/__init__.py
aollio/crawl.py
aollio/fileinput.py
aollio/fileutil.py
aollio/hello.py
aollio/user_agents.txt
aollio-0.1.2.dist-info/DESCRIPTION.rst
aollio-0.1.2.dist-info/METADATA
aollio-0.1.2.dist-info/RECORD
aollio-0.1.2.dist-info/WHEEL
aollio-0.1.2.dist-info/metadata.json
aollio-0.1.2.dist-info/top_level.txt
