Metadata-Version: 2.0
Name: aollio
Version: 0.1.2
Summary: Some simple and funny modules
Home-page: https://github.com/aollio/aollio
Author: Aollio Hou
Author-email: aollio@outlook.com
License: UNKNOWN
Keywords: sample setuptools development
Platform: UNKNOWN
Classifier: Development Status :: 3 - Alpha
Classifier: Intended Audience :: Developers
Classifier: Topic :: Software Development :: Build Tools
Classifier: License :: OSI Approved :: MIT License
Classifier: Programming Language :: Python :: 3
Classifier: Programming Language :: Python :: 3.4
Classifier: Programming Language :: Python :: 3.5
Classifier: Programming Language :: Python :: 3.6
Requires-Dist: peppercorn
